ChalkCli
