Metadata-Version: 2.1
Name: ChalkCli
Version: 0.1.0
Summary: A Python package for terminal text styling and coloring.
Home-page: https://github.com/ishanoshada/ChalkCli
Author: Ishan Oshada
Author-email: Ishan.kodithuwakku.official@gmail.com
License: UNKNOWN
Platform: UNKNOWN
Classifier: Programming Language :: Python :: 3
Classifier: License :: OSI Approved :: MIT License
Classifier: Operating System :: OS Independent
